manim_chemistry/__init__.py
manim_chemistry/bohr_atom/__init__.py
manim_chemistry/bohr_atom/bohr_atom.py
manim_chemistry/element/__init__.py
manim_chemistry/element/element.py
manim_chemistry/future_classes/future_classes.py
manim_chemistry/orbitals/__init__.py
manim_chemistry/orbitals/orbitals.py
manim_chemistry/periodic_table/__init__.py
manim_chemistry/periodic_table/table_objects.py
manim_chemistry/threeD/__init__.py
manim_chemistry/threeD/threedatom.py
manim_chemistry/threeD/threedbond.py
manim_chemistry/threeD/threedmolecule.py
manim_chemistry/threeD/utils.py
manim_chemistry/twoD/__init__.py
manim_chemistry/twoD/animations.py
manim_chemistry/twoD/atom.py
manim_chemistry/twoD/bond.py
manim_chemistry/twoD/chemical_formula.py
manim_chemistry/twoD/graph_molecule.py
manim_chemistry/twoD/molecule.py
manim_chemistry/utils/__init__.py
manim_chemistry/utils/utils.py
manim_chemistry-0.4.4.dist-info/LICENSE.md
manim_chemistry-0.4.4.dist-info/METADATA
manim_chemistry-0.4.4.dist-info/WHEEL
manim_chemistry-0.4.4.dist-info/entry_points.txt
manim_chemistry-0.4.4.dist-info/top_level.txt
manim_chemistry-0.4.4.dist-info/RECORD
