Metadata-Version: 2.2
Name: manim-chemistry
Version: 0.4.4
Summary: Manim Chemistry is a plugin for Manim which aims to make easier the animation of molecules and other chemistry-related objects such as orbitals, bohr diagrams and more.
Author-email: UMDQ <unmoldequimica@gmail.com>
Maintainer-email: UMDQ <unmoldequimica@gmail.com>
License: MIT License
Project-URL: Source, https://github.com/UnMolDeQuimica/manim-Chemistry
Project-URL: Issue tracker, https://github.com/UnMolDeQuimica/manim-Chemistry/issues
Project-URL: Homepage, https://github.com/UnMolDeQuimica/manim-Chemistry
Classifier: Programming Language :: Python :: 3
Classifier: License :: OSI Approved :: MIT License
Classifier: Operating System :: OS Independent
Classifier: Natural Language :: English
Requires-Python: >=3.9
License-File: LICENSE.md
Requires-Dist: manim
Requires-Dist: numpy
Requires-Dist: pandas
